akvo/__init__.py
akvo/gui/Loop.ui
akvo/gui/Loop_ui.py
akvo/gui/Spoiler.py
akvo/gui/__init__.py
akvo/gui/addCircularLoop.ui
akvo/gui/addCircularLoop_ui.py
akvo/gui/addFigure8Loop.ui
akvo/gui/addFigure8Loop_ui.py
akvo/gui/addPolygonalLoop.ui
akvo/gui/addPolygonalLoop_ui.py
akvo/gui/akvo-about.png
akvo/gui/akvo-crop.png
akvo/gui/akvo.png
akvo/gui/akvo2.png
akvo/gui/akvoGUI.py
akvo/gui/callScript.py
akvo/gui/logo.py
akvo/gui/logo2.py
akvo/gui/main-bu.ui
akvo/gui/main.ui
akvo/gui/main2ui.py
akvo/gui/main_ui.py
akvo/gui/mainbu.ui
akvo/gui/mainui2.py
akvo/gui/mydynamicmplcanvas-broke.py
akvo/gui/mydynamicmplcanvas.py
akvo/gui/mydynamicmplcanvasnavigator.py
akvo/gui/redirect.ui
akvo/gui/redirect_ui.py
akvo/gui/scroll.ui
akvo/gui/speak.py
akvo/gui/temp.py
akvo/gui/turtle.png
akvo/tressel/SlidesPlot.py
akvo/tressel/__init__.py
akvo/tressel/adapt.py
akvo/tressel/calcAkvoKernel--save.py
akvo/tressel/calcAkvoKernel.py
akvo/tressel/cmaps.py
akvo/tressel/decay-old.py
akvo/tressel/decay.py
akvo/tressel/filtfilt.py
akvo/tressel/gateIntegrate4.py
akvo/tressel/harmonic.py
akvo/tressel/invertTA.py
akvo/tressel/lemma_yaml.py
akvo/tressel/logbarrier-nnls.py
akvo/tressel/logbarrier.py
akvo/tressel/mrsurvey.py
akvo/tressel/nonlinearinv.py
akvo/tressel/pca.py
akvo/tressel/rotate.py
akvo/tressel/smooth.py
Akvo-1.7.2.dist-info/LICENCE
Akvo-1.7.2.dist-info/LICENSE
Akvo-1.7.2.dist-info/METADATA
Akvo-1.7.2.dist-info/WHEEL
Akvo-1.7.2.dist-info/entry_points.txt
Akvo-1.7.2.dist-info/top_level.txt
Akvo-1.7.2.dist-info/RECORD
