Metadata-Version: 2.1
Name: Akvo
Version: 1.7.2
Summary: Surface nuclear magnetic resonance workbench
Home-page: https://akvo.lemmasoftware.org/
Author: Trevor P. Irons
Author-email: Trevor.Irons@lemmasoftware.org
License: GPL 4.0
Platform: UNKNOWN
Classifier: Programming Language :: Python :: 3
Classifier: License :: OSI Approved :: GNU Lesser General Public License v3 or later (LGPLv3+)
Classifier: Operating System :: OS Independent
Requires-Python: >3.7.0
License-File: LICENCE
License-File: LICENSE
Requires-Dist: matplotlib
Requires-Dist: scipy
Requires-Dist: padasip
Requires-Dist: seaborn
Requires-Dist: numpy
Requires-Dist: pyqt5
Requires-Dist: pyyaml
Requires-Dist: ruamel.yaml
Requires-Dist: pandas
Requires-Dist: pyqt-distutils
Requires-Dist: cmocean
Requires-Dist: pyLemma (>=0.4.0)
